Metadata-Version: 2.1
Name: graphlogger
Version: 0.0.1
Summary: Library to load data sets to Neo4j.
Home-page: https://github.com/kaiserpreusse/graphlogger
Author: Martin Preusse
Author-email: martin.preusse@gmail.com
License: Apache License 2.0
Keywords: NEO4J
Platform: UNKNOWN
Classifier: Programming Language :: Python
Classifier: Intended Audience :: Developers
